wahoomc/__init__.py
wahoomc/__main__.py
wahoomc/constants.py
wahoomc/constants_functions.py
wahoomc/downloader.py
wahoomc/file_directory_functions.py
wahoomc/geofabrik.py
wahoomc/geofabrik_json.py
wahoomc/input.py
wahoomc/main.py
wahoomc/osm_data.py
wahoomc/osm_maps_functions.py
wahoomc/setup_functions.py
wahoomc/timings.py
wahoomc/init/__init__.py
wahoomc/init/__main__.py
wahoomc/resources/sea.osm
wahoomc/resources/shape2osm.py
wahoomc/resources/tags-to-keep.json
wahoomc/resources/tunnel-transform.xml
wahoomc/resources/tag_wahoo_adjusted/tag-wahoo-poi.xml
wahoomc/resources/tag_wahoo_adjusted/tag-wahoo.xml
wahoomc/resources/tag_wahoo_initial/tag-wahoo_original.xml
wahoomc/tooling_win/7za.dll
wahoomc/tooling_win/7za.exe
wahoomc/tooling_win/7zxa.dll
wahoomc/tooling_win/lzma.exe
wahoomc/tooling_win/osmconvert.exe
wahoomc/tooling_win/osmconvert64-0.8.8p.exe
wahoomc-4.3.0.dist-info/LICENSE
wahoomc-4.3.0.dist-info/METADATA
wahoomc-4.3.0.dist-info/WHEEL
wahoomc-4.3.0.dist-info/top_level.txt
wahoomc-4.3.0.dist-info/RECORD
