Metadata-Version: 2.1
Name: wahoomc
Version: 4.3.0
Summary: Create maps for your Wahoo bike computer based on latest OSM maps
Home-page: https://github.com/treee111/wahooMapsCreator
Author: Benjamin Kreuscher
Author-email: benni.kreuscher@gmail.com
Project-URL: Bug Tracker, https://github.com/treee111/wahooMapsCreator/issues
Classifier: Programming Language :: Python :: 3
Classifier: License :: OSI Approved :: MIT License
Classifier: Operating System :: OS Independent
Requires-Python: >=3.10
License-File: LICENSE
